MANIFEST.in
setup.py
QEnvPython39.egg-info/PKG-INFO
QEnvPython39.egg-info/SOURCES.txt
QEnvPython39.egg-info/dependency_links.txt
QEnvPython39.egg-info/top_level.txt
QPT_SDK/__init__.py
QPT_SDK/QEnvPython/__init__.py
QPT_SDK/QEnvPython/python39/LICENSE.txt
QPT_SDK/QEnvPython/python39/_asyncio.pyd
QPT_SDK/QEnvPython/python39/_bz2.pyd
QPT_SDK/QEnvPython/python39/_ctypes.pyd
QPT_SDK/QEnvPython/python39/_decimal.pyd
QPT_SDK/QEnvPython/python39/_elementtree.pyd
QPT_SDK/QEnvPython/python39/_hashlib.pyd
QPT_SDK/QEnvPython/python39/_lzma.pyd
QPT_SDK/QEnvPython/python39/_msi.pyd
QPT_SDK/QEnvPython/python39/_multiprocessing.pyd
QPT_SDK/QEnvPython/python39/_overlapped.pyd
QPT_SDK/QEnvPython/python39/_queue.pyd
QPT_SDK/QEnvPython/python39/_socket.pyd
QPT_SDK/QEnvPython/python39/_sqlite3.pyd
QPT_SDK/QEnvPython/python39/_ssl.pyd
QPT_SDK/QEnvPython/python39/_uuid.pyd
QPT_SDK/QEnvPython/python39/_zoneinfo.pyd
QPT_SDK/QEnvPython/python39/libcrypto-1_1.dll
QPT_SDK/QEnvPython/python39/libffi-7.dll
QPT_SDK/QEnvPython/python39/libssl-1_1.dll
QPT_SDK/QEnvPython/python39/pyexpat.pyd
QPT_SDK/QEnvPython/python39/python.cat
QPT_SDK/QEnvPython/python39/python.exe
QPT_SDK/QEnvPython/python39/python3.dll
QPT_SDK/QEnvPython/python39/python39._pth
QPT_SDK/QEnvPython/python39/python39.dll
QPT_SDK/QEnvPython/python39/python39.zip
QPT_SDK/QEnvPython/python39/pythonw.exe
QPT_SDK/QEnvPython/python39/select.pyd
QPT_SDK/QEnvPython/python39/sqlite3.dll
QPT_SDK/QEnvPython/python39/unicodedata.pyd
QPT_SDK/QEnvPython/python39/vcruntime140.dll
QPT_SDK/QEnvPython/python39/vcruntime140_1.dll
QPT_SDK/QEnvPython/python39/winsound.pyd
QPT_SDK/QEnvPython/python39/Lib/site-packages/distutils-precedence.pth
QPT_SDK/QEnvPython/python39/Lib/site-packages/_distutils_hack/__init__.py
QPT_SDK/QEnvPython/python39/Lib/site-packages/_distutils_hack/override.py
QPT_SDK/QEnvPython/python39/Lib/site-packages/pip/__init__.py
QPT_SDK/QEnvPython/python39/Lib/site-packages/pip/__main__.py
QPT_SDK/QEnvPython/python39/Lib/site-packages/pip/__pip-runner__.py
QPT_SDK/QEnvPython/python39/Lib/site-packages/pip/py.typed
QPT_SDK/QEnvPython/python39/Lib/site-packages/pip-23.3.1.dist-info/AUTHORS.txt
QPT_SDK/QEnvPython/python39/Lib/site-packages/pip-23.3.1.dist-info/INSTALLER
QPT_SDK/QEnvPython/python39/Lib/site-packages/pip-23.3.1.dist-info/LICENSE.txt
QPT_SDK/QEnvPython/python39/Lib/site-packages/pip-23.3.1.dist-info/METADATA
QPT_SDK/QEnvPython/python39/Lib/site-packages/pip-23.3.1.dist-info/RECORD
QPT_SDK/QEnvPython/python39/Lib/site-packages/pip-23.3.1.dist-info/REQUESTED
QPT_SDK/QEnvPython/python39/Lib/site-packages/pip-23.3.1.dist-info/WHEEL
QPT_SDK/QEnvPython/python39/Lib/site-packages/pip-23.3.1.dist-info/entry_points.txt
QPT_SDK/QEnvPython/python39/Lib/site-packages/pip-23.3.1.dist-info/top_level.txt
QPT_SDK/QEnvPython/python39/Lib/site-packages/setuptools-68.2.2.dist-info/INSTALLER
QPT_SDK/QEnvPython/python39/Lib/site-packages/setuptools-68.2.2.dist-info/LICENSE
QPT_SDK/QEnvPython/python39/Lib/site-packages/setuptools-68.2.2.dist-info/METADATA
QPT_SDK/QEnvPython/python39/Lib/site-packages/setuptools-68.2.2.dist-info/RECORD
QPT_SDK/QEnvPython/python39/Lib/site-packages/setuptools-68.2.2.dist-info/REQUESTED
QPT_SDK/QEnvPython/python39/Lib/site-packages/setuptools-68.2.2.dist-info/WHEEL
QPT_SDK/QEnvPython/python39/Lib/site-packages/setuptools-68.2.2.dist-info/entry_points.txt
QPT_SDK/QEnvPython/python39/Lib/site-packages/setuptools-68.2.2.dist-info/top_level.txt
QPT_SDK/QEnvPython/python39/Lib/site-packages/wheel-0.41.3.dist-info/INSTALLER
QPT_SDK/QEnvPython/python39/Lib/site-packages/wheel-0.41.3.dist-info/LICENSE.txt
QPT_SDK/QEnvPython/python39/Lib/site-packages/wheel-0.41.3.dist-info/METADATA
QPT_SDK/QEnvPython/python39/Lib/site-packages/wheel-0.41.3.dist-info/RECORD
QPT_SDK/QEnvPython/python39/Lib/site-packages/wheel-0.41.3.dist-info/REQUESTED
QPT_SDK/QEnvPython/python39/Lib/site-packages/wheel-0.41.3.dist-info/WHEEL
QPT_SDK/QEnvPython/python39/Lib/site-packages/wheel-0.41.3.dist-info/entry_points.txt
