Metadata-Version: 2.1
Name: QEnvPython39
Version: 3.9.13
Summary: QPT-Python环境打包工具 SDK
Home-page: https://github.com/GT-ZhangAcer/QPT
Author: GT-ZhangAcer
Author-email: zhangacer@foxmail.com
License: MIT
